msaJustPyUI
